cerberus_document_editor/__init__.py
cerberus_document_editor/__main__.py
cerberus_document_editor/debug.py
cerberus_document_editor/editor.py
cerberus_document_editor/model.py
cerberus_document_editor/page.py
cerberus_document_editor/user_page.py
cerberus_document_editor/validator.py
cerberus_document_editor/widget.py
cerberus_document_editor/yaml_parser.py
cerberus_document_editor-0.0.9.dist-info/LICENSE
cerberus_document_editor-0.0.9.dist-info/METADATA
cerberus_document_editor-0.0.9.dist-info/WHEEL
cerberus_document_editor-0.0.9.dist-info/entry_points.txt
cerberus_document_editor-0.0.9.dist-info/top_level.txt
cerberus_document_editor-0.0.9.dist-info/RECORD
