Metadata-Version: 2.1
Name: cerberus-document-editor
Version: 0.0.9
Summary: Document Editor for Cerberus Schema.
Home-page: https://github.com/onetop21/cerberus-document-editor.git
Author: Hyoil LEE
Author-email: onetop21@gmail.com
License: MIT License
Platform: UNKNOWN
Requires-Python: >=3.0
License-File: LICENSE
Requires-Dist: cerberus-kind (<1.0.0,>=0.0.17)
Requires-Dist: PyYAML (<6.0.0,>=5.4.1)
Requires-Dist: urwid (<3.0.0,>=2.1.2)
Requires-Dist: InterruptHandler (<1.0.0,>=0.0.4)
